ace_authorize/__init__.py
ace_authorize-0.1.15.dist-info/LICENSE
ace_authorize-0.1.15.dist-info/METADATA
ace_authorize-0.1.15.dist-info/WHEEL
ace_authorize-0.1.15.dist-info/top_level.txt
ace_authorize-0.1.15.dist-info/RECORD
