Metadata-Version: 2.1
Name: ace-authorize
Version: 0.1.15
Summary: A small authorisation decorator package for the ACE project
Home-page: https://github.com/IncentroNext/ace-utils/tree/feature/ace_authorize/ace_authorize
Author: Jesse Koekkoek
Author-email: jesse.koekkoek@incentro.com
License: UNKNOWN
Project-URL: Bug Tracker, https://github.com/IncentroNext/ace-utils/issues
Platform: UNKNOWN
Classifier: Programming Language :: Python :: 3
Classifier: License :: OSI Approved :: MIT License
Classifier: Operating System :: OS Independent
Requires-Python: >=3.6
License-File: LICENSE
